{"tu":{"x":143,"y":81,"tc":"FF3333"},"rx":{"w":16,"h":16,"x":1,"y":1,"a":"tr","rep":"wgt"},"lu":{"x":242,"y":149,"tc":"00AAAA"},"gt":{"x":51,"y":62,"w":86,"tf":"m","tc":"FF3333","ta":"r"},"grx":{"x":242,"y":127,"tc":"00AAAA"},"tilt":{"x":219,"y":62,"tf":"m","tc":"5555DD"},"bat":{"x":242,"y":105,"tc":"00AAAA"},"sg":{"x":129,"y":11,"tf":"l","tc":"33FF33"},"og":{"x":66,"y":105,"tc":"00AAAA"},"abv":{"x":66,"y":127,"tc":"00AAAA"},"att":{"x":66,"y":149,"tc":"00AAAA"},"stxt":[{"x":8,"w":280,"tx":"RAPT Pill Hydrometer"},{"x":61,"y":47,"tx":"Gravity"},{"x":11,"y":80,"tx":"Temp"},{"x":169,"y":80,"tx":"Angle"},{"x":29,"y":105,"tx":"OG"},{"x":23,"y":127,"tx":"ABV"},{"x":28,"y":149,"tx":"ATT"},{"x":167,"y":105,"tx":"Battery"},{"x":186,"y":127,"tx":"RSSI"},{"x":152,"y":149,"tx":"Last Seen"}]}